{"torneo_2022": {"0": {"data": "08-11-2022 16:00:00", "gironi": "A Femminile", "genere_gironi": 0, "squadra_1": "HELLAS MA-DONNE", "squadra_2": "LA BALLA IN FIESTA", "gol_squadra_1": 0, "gol_squadra_2": 0, "falli_squadra_1": 0, "falli_squadra_2": 0, "gialli1": "", "gialli2": "", "rossi1": "", "rossi2": "", "goleador_1": "{}", "goleador_2": "{}", "autogol1": "{}", "autogol2": "{}", "best_giocatore_1": {}, "best_giocatore_2": {}, "best_portiere_1": {}, "best_portiere_2": {}, "note": ""}, "1": {"data": "08-11-2022 16:20:00", "gironi": "B Maschile", "genere_gironi": 1, "squadra_1": "MAI UNA GIOIA", "squadra_2": "SBARX", "gol_squadra_1": 0, "gol_squadra_2": 0, "falli_squadra_1": 0, "falli_squadra_2": 0, "gialli1": "", "gialli2": "", "rossi1": "", "rossi2": "", "goleador_1": "{}", "goleador_2": "{}", "autogol1": "{}", "autogol2": "{}", "best_giocatore_1": {}, "best_giocatore_2": {}, "best_portiere_1": {}, "best_portiere_2": {}, "note": ""}, "2": {"data": "08-11-2022 16:40:00", "gironi": "A Maschile", "genere_gironi": 1, "squadra_1": "FC SAVIGNANO", "squadra_2": "FEL LAZIO", "gol_squadra_1": 0, "gol_squadra_2": 0, "falli_squadra_1": 0, "falli_squadra_2": 0, "gialli1": "", "gialli2": "", "rossi1": "", "rossi2": "", "goleador_1": "{}", "goleador_2": "{}", "autogol1": "{}", "autogol2": "{}", "best_giocatore_1": {}, "best_giocatore_2": {}, "best_portiere_1": {}, "best_portiere_2": {}, "note": ""}, "3": {"data": "08-11-2022 17:00:00", "gironi": "H Maschile", "genere_gironi": 1, "squadra_1": "INEFUMA ELEVEN", "squadra_2": "RESENTEAM", "gol_squadra_1": 0, "gol_squadra_2": 0, "falli_squadra_1": 0, "falli_squadra_2": 0, "gialli1": "", "gialli2": "", "rossi1": "", "rossi2": "", "goleador_1": "{}", "goleador_2": "{}", "autogol1": "{}", "autogol2": "{}", "best_giocatore_1": {}, "best_giocatore_2": {}, "best_portiere_1": {}, "best_portiere_2": {}, "note": ""}, "4": {"data": "08-11-2022 17:20:00", "gironi": "G Maschile", "genere_gironi": 1, "squadra_1": "NAZIONALE FERROVIERI", "squadra_2": "DEMO BUSTERS", "gol_squadra_1": 0, "gol_squadra_2": 0, "falli_squadra_1": 0, "falli_squadra_2": 0, "gialli1": "", "gialli2": "", "rossi1": "", "rossi2": "", "goleador_1": "{}", "goleador_2": "{}", "autogol1": "{}", "autogol2": "{}", "best_giocatore_1": {}, "best_giocatore_2": {}, "best_portiere_1": {}, "best_portiere_2": {}, "note": ""}, "5": {"data": "08-11-2022 17:40:00", "gironi": "A Maschile", "genere_gironi": 1, "squadra_1": "SHARK ATTACK", "squadra_2": "I MAGNIFICI", "gol_squadra_1": 0, "gol_squadra_2": 0, "falli_squadra_1": 0, "falli_squadra_2": 0, "gialli1": "", "gialli2": "", "rossi1": "", "rossi2": "", "goleador_1": "{}", "goleador_2": "{}", "autogol1": "{}", "autogol2": "{}", "best_giocatore_1": {}, "best_giocatore_2": {}, "best_portiere_1": {}, "best_portiere_2": {}, "note": ""}, "6": {"data": "08-11-2022 18:00:00", "gironi": "G Maschile", "genere_gironi": 1, "squadra_1": "ATLETICO MA NON TROPPO", "squadra_2": "POWER GINGER", "gol_squadra_1": 0, "gol_squadra_2": 0, "falli_squadra_1": 0, "falli_squadra_2": 0, "gialli1": "", "gialli2": "", "rossi1": "", "rossi2": "", "goleador_1": "{}", "goleador_2": "{}", "autogol1": "{}", "autogol2": "{}", "best_giocatore_1": {}, "best_giocatore_2": {}, "best_portiere_1": {}, "best_portiere_2": {}, "note": ""}, "7": {"data": "08-11-2022 18:20:00", "gironi": "B Femminile", "genere_gironi": 0, "squadra_1": "GIN TONICHE", "squadra_2": "GREENPASSERE", "gol_squadra_1": 0, "gol_squadra_2": 0, "falli_squadra_1": 0, "falli_squadra_2": 0, "gialli1": "", "gialli2": "", "rossi1": "", "rossi2": "", "goleador_1": "{}", "goleador_2": "{}", "autogol1": "{}", "autogol2": "{}", "best_giocatore_1": {}, "best_giocatore_2": {}, "best_portiere_1": {}, "best_portiere_2": {}, "note": ""}, "8": {"data": "08-11-2022 18:40:00", "gironi": "D Maschile", "genere_gironi": 1, "squadra_1": "ORANGE OLD SCHOOL", "squadra_2": "TECNICA & CACAO", "gol_squadra_1": 0, "gol_squadra_2": 0, "falli_squadra_1": 0, "falli_squadra_2": 0, "gialli1": "", "gialli2": "", "rossi1": "", "rossi2": "", "goleador_1": "{}", "goleador_2": "{}", "autogol1": "{}", "autogol2": "{}", "best_giocatore_1": {}, "best_giocatore_2": {}, "best_portiere_1": {}, "best_portiere_2": {}, "note": ""}, "9": {"data": "08-11-2022 19:00:00", "gironi": "C Femminile", "genere_gironi": 0, "squadra_1": "DRIM TIM", "squadra_2": "TORTE DI MELE", "gol_squadra_1": 0, "gol_squadra_2": 0, "falli_squadra_1": 0, "falli_squadra_2": 0, "gialli1": "", "gialli2": "", "rossi1": "", "rossi2": "", "goleador_1": "{}", "goleador_2": "{}", "autogol1": "{}", "autogol2": "{}", "best_giocatore_1": {}, "best_giocatore_2": {}, "best_portiere_1": {}, "best_portiere_2": {}, "note": ""}, "10": {"data": "08-11-2022 19:20:00", "gironi": "C Maschile", "genere_gironi": 1, "squadra_1": "PINGUINI TRENTINI", "squadra_2": "CLANDES TEAM", "gol_squadra_1": 0, "gol_squadra_2": 0, "falli_squadra_1": 0, "falli_squadra_2": 0, "gialli1": "", "gialli2": "", "rossi1": "", "rossi2": "", "goleador_1": "{}", "goleador_2": "{}", "autogol1": "{}", "autogol2": "{}", "best_giocatore_1": {}, "best_giocatore_2": {}, "best_portiere_1": {}, "best_portiere_2": {}, "note": ""}, "11": {"data": "08-11-2022 19:40:00", "gironi": "F Maschile", "genere_gironi": 1, "squadra_1": "CLITORIDERS", "squadra_2": "FIGLI DI UN RE MINORE", "gol_squadra_1": 0, "gol_squadra_2": 0, "falli_squadra_1": 0, "falli_squadra_2": 0, "gialli1": "", "gialli2": "", "rossi1": "", "rossi2": "", "goleador_1": "{}", "goleador_2": "{}", "autogol1": "{}", "autogol2": "{}", "best_giocatore_1": {}, "best_giocatore_2": {}, "best_portiere_1": {}, "best_portiere_2": {}, "note": ""}, "12": {"data": "08-11-2022 20:00:00", "gironi": "H Maschile", "genere_gironi": 1, "squadra_1": "LA CONTEA FC", "squadra_2": "SPRINT GOMMA TEAM", "gol_squadra_1": 0, "gol_squadra_2": 0, "falli_squadra_1": 0, "falli_squadra_2": 0, "gialli1": "", "gialli2": "", "rossi1": "", "rossi2": "", "goleador_1": "{}", "goleador_2": "{}", "autogol1": "{}", "autogol2": "{}", "best_giocatore_1": {}, "best_giocatore_2": {}, "best_portiere_1": {}, "best_portiere_2": {}, "note": ""}, "13": {"data": "08-11-2022 20:20:00", "gironi": "E Maschile", "genere_gironi": 1, "squadra_1": "I MODIUM", "squadra_2": "MEDIASER.T", "gol_squadra_1": 0, "gol_squadra_2": 0, "falli_squadra_1": 0, "falli_squadra_2": 0, "gialli1": "", "gialli2": "", "rossi1": "", "rossi2": "", "goleador_1": "{}", "goleador_2": "{}", "autogol1": "{}", "autogol2": "{}", "best_giocatore_1": {}, "best_giocatore_2": {}, "best_portiere_1": {}, "best_portiere_2": {}, "note": ""}, "14": {"data": "08-11-2022 21:00:00", "gironi": "B Femminile", "genere_gironi": 0, "squadra_1": "AL VOLO", "squadra_2": "MOCCIO(SE)", "gol_squadra_1": 0, "gol_squadra_2": 0, "falli_squadra_1": 0, "falli_squadra_2": 0, "gialli1": "", "gialli2": "", "rossi1": "", "rossi2": "", "goleador_1": "{}", "goleador_2": "{}", "autogol1": "{}", "autogol2": "{}", "best_giocatore_1": {}, "best_giocatore_2": {}, "best_portiere_1": {}, "best_portiere_2": {}, "note": ""}, "15": {"data": "08-11-2022 21:20:00", "gironi": "B Maschile", "genere_gironi": 1, "squadra_1": "SBARX", "squadra_2": "US GUARNA", "gol_squadra_1": 0, "gol_squadra_2": 0, "falli_squadra_1": 0, "falli_squadra_2": 0, "gialli1": "", "gialli2": "", "rossi1": "", "rossi2": "", "goleador_1": "{}", "goleador_2": "{}", "autogol1": "{}", "autogol2": "{}", "best_giocatore_1": {}, "best_giocatore_2": {}, "best_portiere_1": {}, "best_portiere_2": {}, "note": ""}, "16": {"data": "08-11-2022 21:40:00", "gironi": "C Femminile", "genere_gironi": 0, "squadra_1": "TANGATUBBIES", "squadra_2": "DRIM TIM", "gol_squadra_1": 0, "gol_squadra_2": 0, "falli_squadra_1": 0, "falli_squadra_2": 0, "gialli1": "", "gialli2": "", "rossi1": "", "rossi2": "", "goleador_1": "{}", "goleador_2": "{}", "autogol1": "{}", "autogol2": "{}", "best_giocatore_1": {}, "best_giocatore_2": {}, "best_portiere_1": {}, "best_portiere_2": {}, "note": ""}, "17": {"data": "08-11-2022 22:00:00", "gironi": "F Maschile", "genere_gironi": 1, "squadra_1": "FIGLI DI UN RE MINORE", "squadra_2": "HELLAS MADONNA", "gol_squadra_1": 0, "gol_squadra_2": 0, "falli_squadra_1": 0, "falli_squadra_2": 0, "gialli1": "", "gialli2": "", "rossi1": "", "rossi2": "", "goleador_1": "{}", "goleador_2": "{}", "autogol1": "{}", "autogol2": "{}", "best_giocatore_1": {}, "best_giocatore_2": {}, "best_portiere_1": {}, "best_portiere_2": {}, "note": ""}, "18": {"data": "08-11-2022 22:20:00", "gironi": "D Femminile", "genere_gironi": 0, "squadra_1": "FC WANDA TEAM GIRLS", "squadra_2": "LEMONADE", "gol_squadra_1": 0, "gol_squadra_2": 0, "falli_squadra_1": 0, "falli_squadra_2": 0, "gialli1": "", "gialli2": "", "rossi1": "", "rossi2": "", "goleador_1": "{}", "goleador_2": "{}", "autogol1": "{}", "autogol2": "{}", "best_giocatore_1": {}, "best_giocatore_2": {}, "best_portiere_1": {}, "best_portiere_2": {}, "note": ""}, "19": {"data": "08-11-2022 22:40:00", "gironi": "C Maschile", "genere_gironi": 1, "squadra_1": "I MONTAGNA", "squadra_2": "BELLA DOMANDA", "gol_squadra_1": 0, "gol_squadra_2": 0, "falli_squadra_1": 0, "falli_squadra_2": 0, "gialli1": "", "gialli2": "", "rossi1": "", "rossi2": "", "goleador_1": "{}", "goleador_2": "{}", "autogol1": "{}", "autogol2": "{}", "best_giocatore_1": {}, "best_giocatore_2": {}, "best_portiere_1": {}, "best_portiere_2": {}, "note": ""}, "20": {"data": "08-11-2022 23:00:00", "gironi": "D Femminile", "genere_gironi": 0, "squadra_1": "CHICASMALAS", "squadra_2": "TETTA PIG", "gol_squadra_1": 0, "gol_squadra_2": 0, "falli_squadra_1": 0, "falli_squadra_2": 0, "gialli1": "", "gialli2": "", "rossi1": "", "rossi2": "", "goleador_1": "{}", "goleador_2": "{}", "autogol1": "{}", "autogol2": "{}", "best_giocatore_1": {}, "best_giocatore_2": {}, "best_portiere_1": {}, "best_portiere_2": {}, "note": ""}, "21": {"data": "08-11-2022 23:20:00", "gironi": "E Maschile", "genere_gironi": 1, "squadra_1": "BUONA LA MERDA", "squadra_2": "FC WANDA TEAM", "gol_squadra_1": 0, "gol_squadra_2": 0, "falli_squadra_1": 0, "falli_squadra_2": 0, "gialli1": "", "gialli2": "", "rossi1": "", "rossi2": "", "goleador_1": "{}", "goleador_2": "{}", "autogol1": "{}", "autogol2": "{}", "best_giocatore_1": {}, "best_giocatore_2": {}, "best_portiere_1": {}, "best_portiere_2": {}, "note": ""}, "22": {"data": "08-11-2022 23:40:00", "gironi": "D Maschile", "genere_gironi": 1, "squadra_1": "ONLYFUK", "squadra_2": "CGB GAMBERONI", "gol_squadra_1": 0, "gol_squadra_2": 0, "falli_squadra_1": 0, "falli_squadra_2": 0, "gialli1": "", "gialli2": "", "rossi1": "", "rossi2": "", "goleador_1": "{}", "goleador_2": "{}", "autogol1": "{}", "autogol2": "{}", "best_giocatore_1": {}, "best_giocatore_2": {}, "best_portiere_1": {}, "best_portiere_2": {}, "note": ""}, "23": {"data": "08-12-2022 16:00:00", "gironi": "B Femminile", "genere_gironi": 0, "squadra_1": "GIN TONICHE", "squadra_2": "MOCCIO(SE)", "gol_squadra_1": 0, "gol_squadra_2": 0, "falli_squadra_1": 0, "falli_squadra_2": 0, "gialli1": "", "gialli2": "", "rossi1": "", "rossi2": "", "goleador_1": "{}", "goleador_2": "{}", "autogol1": "{}", "autogol2": "{}", "best_giocatore_1": {}, "best_giocatore_2": {}, "best_portiere_1": {}, "best_portiere_2": {}, "note": ""}, "24": {"data": "08-12-2022 16:20:00", "gironi": "A Maschile", "genere_gironi": 1, "squadra_1": "FC SAVIGNANO", "squadra_2": "I MAGNIFICI", "gol_squadra_1": 0, "gol_squadra_2": 0, "falli_squadra_1": 0, "falli_squadra_2": 0, "gialli1": "", "gialli2": "", "rossi1": "", "rossi2": "", "goleador_1": "{}", "goleador_2": "{}", "autogol1": "{}", "autogol2": "{}", "best_giocatore_1": {}, "best_giocatore_2": {}, "best_portiere_1": {}, "best_portiere_2": {}, "note": ""}, "25": {"data": "08-12-2022 16:40:00", "gironi": "D Femminile", "genere_gironi": 0, "squadra_1": "FC WANDA TEAM GIRLS", "squadra_2": "TETTA PIG", "gol_squadra_1": 0, "gol_squadra_2": 0, "falli_squadra_1": 0, "falli_squadra_2": 0, "gialli1": "", "gialli2": "", "rossi1": "", "rossi2": "", "goleador_1": "{}", "goleador_2": "{}", "autogol1": "{}", "autogol2": "{}", "best_giocatore_1": {}, "best_giocatore_2": {}, "best_portiere_1": {}, "best_portiere_2": {}, "note": ""}, "26": {"data": "08-12-2022 17:00:00", "gironi": "E Maschile", "genere_gironi": 1, "squadra_1": "FC WANDA TEAM", "squadra_2": "I MODIUM", "gol_squadra_1": 0, "gol_squadra_2": 0, "falli_squadra_1": 0, "falli_squadra_2": 0, "gialli1": "", "gialli2": "", "rossi1": "", "rossi2": "", "goleador_1": "{}", "goleador_2": "{}", "autogol1": "{}", "autogol2": "{}", "best_giocatore_1": {}, "best_giocatore_2": {}, "best_portiere_1": {}, "best_portiere_2": {}, "note": ""}, "27": {"data": "08-12-2022 17:20:00", "gironi": "A Femminile", "genere_gironi": 0, "squadra_1": "HELLAS MA-DONNE", "squadra_2": "POCHE MA BONE", "gol_squadra_1": 0, "gol_squadra_2": 0, "falli_squadra_1": 0, "falli_squadra_2": 0, "gialli1": "", "gialli2": "", "rossi1": "", "rossi2": "", "goleador_1": "{}", "goleador_2": "{}", "autogol1": "{}", "autogol2": "{}", "best_giocatore_1": {}, "best_giocatore_2": {}, "best_portiere_1": {}, "best_portiere_2": {}, "note": ""}, "28": {"data": "08-12-2022 17:40:00", "gironi": "B Femminile", "genere_gironi": 0, "squadra_1": "AL VOLO", "squadra_2": "GREENPASSERE", "gol_squadra_1": 0, "gol_squadra_2": 0, "falli_squadra_1": 0, "falli_squadra_2": 0, "gialli1": "", "gialli2": "", "rossi1": "", "rossi2": "", "goleador_1": "{}", "goleador_2": "{}", "autogol1": "{}", "autogol2": "{}", "best_giocatore_1": {}, "best_giocatore_2": {}, "best_portiere_1": {}, "best_portiere_2": {}, "note": ""}, "29": {"data": "08-12-2022 18:00:00", "gironi": "G Maschile", "genere_gironi": 1, "squadra_1": "NAZIONALE FERROVIERI", "squadra_2": "ATLETICO MA NON TROPPO", "gol_squadra_1": 0, "gol_squadra_2": 0, "falli_squadra_1": 0, "falli_squadra_2": 0, "gialli1": "", "gialli2": "", "rossi1": "", "rossi2": "", "goleador_1": "{}", "goleador_2": "{}", "autogol1": "{}", "autogol2": "{}", "best_giocatore_1": {}, "best_giocatore_2": {}, "best_portiere_1": {}, "best_portiere_2": {}, "note": ""}, "30": {"data": "08-12-2022 18:20:00", "gironi": "D Maschile", "genere_gironi": 1, "squadra_1": "ORANGE OLD SCHOOL", "squadra_2": "CGB GAMBERONI", "gol_squadra_1": 0, "gol_squadra_2": 0, "falli_squadra_1": 0, "falli_squadra_2": 0, "gialli1": "", "gialli2": "", "rossi1": "", "rossi2": "", "goleador_1": "{}", "goleador_2": "{}", "autogol1": "{}", "autogol2": "{}", "best_giocatore_1": {}, "best_giocatore_2": {}, "best_portiere_1": {}, "best_portiere_2": {}, "note": ""}, "31": {"data": "08-12-2022 18:40:00", "gironi": "H Maschile", "genere_gironi": 1, "squadra_1": "SPRINT GOMMA TEAM", "squadra_2": "INEFUMA ELEVEN", "gol_squadra_1": 0, "gol_squadra_2": 0, "falli_squadra_1": 0, "falli_squadra_2": 0, "gialli1": "", "gialli2": "", "rossi1": "", "rossi2": "", "goleador_1": "{}", "goleador_2": "{}", "autogol1": "{}", "autogol2": "{}", "best_giocatore_1": {}, "best_giocatore_2": {}, "best_portiere_1": {}, "best_portiere_2": {}, "note": ""}, "32": {"data": "08-12-2022 19:00:00", "gironi": "B Maschile", "genere_gironi": 1, "squadra_1": "US GUARNA", "squadra_2": "PRATO FIORITO", "gol_squadra_1": 0, "gol_squadra_2": 0, "falli_squadra_1": 0, "falli_squadra_2": 0, "gialli1": "", "gialli2": "", "rossi1": "", "rossi2": "", "goleador_1": "{}", "goleador_2": "{}", "autogol1": "{}", "autogol2": "{}", "best_giocatore_1": {}, "best_giocatore_2": {}, "best_portiere_1": {}, "best_portiere_2": {}, "note": ""}, "33": {"data": "08-12-2022 19:20:00", "gironi": "F Maschile", "genere_gironi": 1, "squadra_1": "LIZZANELLA'S OLD SUGHI", "squadra_2": "FIGLI DI UN RE MINORE", "gol_squadra_1": 0, "gol_squadra_2": 0, "falli_squadra_1": 0, "falli_squadra_2": 0, "gialli1": "", "gialli2": "", "rossi1": "", "rossi2": "", "goleador_1": "{}", "goleador_2": "{}", "autogol1": "{}", "autogol2": "{}", "best_giocatore_1": {}, "best_giocatore_2": {}, "best_portiere_1": {}, "best_portiere_2": {}, "note": ""}, "34": {"data": "08-12-2022 19:40:00", "gironi": "A Maschile", "genere_gironi": 1, "squadra_1": "SHARK ATTACK", "squadra_2": "FEL LAZIO", "gol_squadra_1": 0, "gol_squadra_2": 0, "falli_squadra_1": 0, "falli_squadra_2": 0, "gialli1": "", "gialli2": "", "rossi1": "", "rossi2": "", "goleador_1": "{}", "goleador_2": "{}", "autogol1": "{}", "autogol2": "{}", "best_giocatore_1": {}, "best_giocatore_2": {}, "best_portiere_1": {}, "best_portiere_2": {}, "note": ""}, "35": {"data": "08-12-2022 20:00:00", "gironi": "C Femminile", "genere_gironi": 0, "squadra_1": "TANGATUBBIES", "squadra_2": "TORTE DI MELE", "gol_squadra_1": 0, "gol_squadra_2": 0, "falli_squadra_1": 0, "falli_squadra_2": 0, "gialli1": "", "gialli2": "", "rossi1": "", "rossi2": "", "goleador_1": "{}", "goleador_2": "{}", "autogol1": "{}", "autogol2": "{}", "best_giocatore_1": {}, "best_giocatore_2": {}, "best_portiere_1": {}, "best_portiere_2": {}, "note": ""}, "36": {"data": "08-12-2022 20:20:00", "gironi": "E Maschile", "genere_gironi": 1, "squadra_1": "MEDIASER.T", "squadra_2": "FC WANDA TEAM", "gol_squadra_1": 0, "gol_squadra_2": 0, "falli_squadra_1": 0, "falli_squadra_2": 0, "gialli1": "", "gialli2": "", "rossi1": "", "rossi2": "", "goleador_1": "{}", "goleador_2": "{}", "autogol1": "{}", "autogol2": "{}", "best_giocatore_1": {}, "best_giocatore_2": {}, "best_portiere_1": {}, "best_portiere_2": {}, "note": ""}, "37": {"data": "08-12-2022 21:00:00", "gironi": "D Femminile", "genere_gironi": 0, "squadra_1": "CHICASMALAS", "squadra_2": "LEMONADE", "gol_squadra_1": 0, "gol_squadra_2": 0, "falli_squadra_1": 0, "falli_squadra_2": 0, "gialli1": "", "gialli2": "", "rossi1": "", "rossi2": "", "goleador_1": "{}", "goleador_2": "{}", "autogol1": "{}", "autogol2": "{}", "best_giocatore_1": {}, "best_giocatore_2": {}, "best_portiere_1": {}, "best_portiere_2": {}, "note": ""}, "38": {"data": "08-12-2022 21:20:00", "gironi": "D Maschile", "genere_gironi": 1, "squadra_1": "TECNICA & CACAO", "squadra_2": "CGB GAMBERONI", "gol_squadra_1": 0, "gol_squadra_2": 0, "falli_squadra_1": 0, "falli_squadra_2": 0, "gialli1": "", "gialli2": "", "rossi1": "", "rossi2": "", "goleador_1": "{}", "goleador_2": "{}", "autogol1": "{}", "autogol2": "{}", "best_giocatore_1": {}, "best_giocatore_2": {}, "best_portiere_1": {}, "best_portiere_2": {}, "note": ""}, "39": {"data": "08-12-2022 21:40:00", "gironi": "B Maschile", "genere_gironi": 1, "squadra_1": "PRATO FIORITO", "squadra_2": "SBARX", "gol_squadra_1": 0, "gol_squadra_2": 0, "falli_squadra_1": 0, "falli_squadra_2": 0, "gialli1": "", "gialli2": "", "rossi1": "", "rossi2": "", "goleador_1": "{}", "goleador_2": "{}", "autogol1": "{}", "autogol2": "{}", "best_giocatore_1": {}, "best_giocatore_2": {}, "best_portiere_1": {}, "best_portiere_2": {}, "note": ""}, "40": {"data": "08-12-2022 22:00:00", "gironi": "C Maschile", "genere_gironi": 1, "squadra_1": "PINGUINI TRENTINI", "squadra_2": "BELLA DOMANDA", "gol_squadra_1": 0, "gol_squadra_2": 0, "falli_squadra_1": 0, "falli_squadra_2": 0, "gialli1": "", "gialli2": "", "rossi1": "", "rossi2": "", "goleador_1": "{}", "goleador_2": "{}", "autogol1": "{}", "autogol2": "{}", "best_giocatore_1": {}, "best_giocatore_2": {}, "best_portiere_1": {}, "best_portiere_2": {}, "note": ""}, "41": {"data": "08-12-2022 22:20:00", "gironi": "A Femminile", "genere_gironi": 0, "squadra_1": "FOUR TAIE + 1", "squadra_2": "LA BALLA IN FIESTA", "gol_squadra_1": 0, "gol_squadra_2": 0, "falli_squadra_1": 0, "falli_squadra_2": 0, "gialli1": "", "gialli2": "", "rossi1": "", "rossi2": "", "goleador_1": "{}", "goleador_2": "{}", "autogol1": "{}", "autogol2": "{}", "best_giocatore_1": {}, "best_giocatore_2": {}, "best_portiere_1": {}, "best_portiere_2": {}, "note": ""}, "42": {"data": "08-13-2022 10:00:00", "gironi": "C Femminile", "genere_gironi": 0, "squadra_1": "SAILOR MONE", "squadra_2": "TANGATUBBIES", "gol_squadra_1": 0, "gol_squadra_2": 0, "falli_squadra_1": 0, "falli_squadra_2": 0, "gialli1": "", "gialli2": "", "rossi1": "", "rossi2": "", "goleador_1": "{}", "goleador_2": "{}", "autogol1": "{}", "autogol2": "{}", "best_giocatore_1": {}, "best_giocatore_2": {}, "best_portiere_1": {}, "best_portiere_2": {}, "note": ""}, "43": {"data": "08-13-2022 10:20:00", "gironi": "A Femminile", "genere_gironi": 0, "squadra_1": "POCHE MA BONE", "squadra_2": "LA BALLA IN FIESTA", "gol_squadra_1": 0, "gol_squadra_2": 0, "falli_squadra_1": 0, "falli_squadra_2": 0, "gialli1": "", "gialli2": "", "rossi1": "", "rossi2": "", "goleador_1": "{}", "goleador_2": "{}", "autogol1": "{}", "autogol2": "{}", "best_giocatore_1": {}, "best_giocatore_2": {}, "best_portiere_1": {}, "best_portiere_2": {}, "note": ""}, "44": {"data": "08-13-2022 10:40:00", "gironi": "H Maschile", "genere_gironi": 1, "squadra_1": "SPRINT GOMMA TEAM", "squadra_2": "RESENTEAM", "gol_squadra_1": 0, "gol_squadra_2": 0, "falli_squadra_1": 0, "falli_squadra_2": 0, "gialli1": "", "gialli2": "", "rossi1": "", "rossi2": "", "goleador_1": "{}", "goleador_2": "{}", "autogol1": "{}", "autogol2": "{}", "best_giocatore_1": {}, "best_giocatore_2": {}, "best_portiere_1": {}, "best_portiere_2": {}, "note": ""}, "45": {"data": "08-13-2022 11:00:00", "gironi": "D Femminile", "genere_gironi": 0, "squadra_1": "LEMONADE", "squadra_2": "TETTA PIG", "gol_squadra_1": 0, "gol_squadra_2": 0, "falli_squadra_1": 0, "falli_squadra_2": 0, "gialli1": "", "gialli2": "", "rossi1": "", "rossi2": "", "goleador_1": "{}", "goleador_2": "{}", "autogol1": "{}", "autogol2": "{}", "best_giocatore_1": {}, "best_giocatore_2": {}, "best_portiere_1": {}, "best_portiere_2": {}, "note": ""}, "46": {"data": "08-13-2022 11:20:00", "gironi": "G Maschile", "genere_gironi": 1, "squadra_1": "DEMO BUSTERS", "squadra_2": "POWER GINGER", "gol_squadra_1": 0, "gol_squadra_2": 0, "falli_squadra_1": 0, "falli_squadra_2": 0, "gialli1": "", "gialli2": "", "rossi1": "", "rossi2": "", "goleador_1": "{}", "goleador_2": "{}", "autogol1": "{}", "autogol2": "{}", "best_giocatore_1": {}, "best_giocatore_2": {}, "best_portiere_1": {}, "best_portiere_2": {}, "note": ""}, "47": {"data": "08-13-2022 11:40:00", "gironi": "A Femminile", "genere_gironi": 0, "squadra_1": "HELLAS MA-DONNE", "squadra_2": "FOUR TAIE + 1", "gol_squadra_1": 0, "gol_squadra_2": 0, "falli_squadra_1": 0, "falli_squadra_2": 0, "gialli1": "", "gialli2": "", "rossi1": "", "rossi2": "", "goleador_1": "{}", "goleador_2": "{}", "autogol1": "{}", "autogol2": "{}", "best_giocatore_1": {}, "best_giocatore_2": {}, "best_portiere_1": {}, "best_portiere_2": {}, "note": ""}, "48": {"data": "08-13-2022 12:00:00", "gironi": "C Femminile", "genere_gironi": 0, "squadra_1": "SAILOR MONE", "squadra_2": "DRIM TIM", "gol_squadra_1": 0, "gol_squadra_2": 0, "falli_squadra_1": 0, "falli_squadra_2": 0, "gialli1": "", "gialli2": "", "rossi1": "", "rossi2": "", "goleador_1": "{}", "goleador_2": "{}", "autogol1": "{}", "autogol2": "{}", "best_giocatore_1": {}, "best_giocatore_2": {}, "best_portiere_1": {}, "best_portiere_2": {}, "note": ""}, "49": {"data": "08-13-2022 12:20:00", "gironi": "D Maschile", "genere_gironi": 1, "squadra_1": "ONLYFUK", "squadra_2": "TECNICA & CACAO", "gol_squadra_1": 0, "gol_squadra_2": 0, "falli_squadra_1": 0, "falli_squadra_2": 0, "gialli1": "", "gialli2": "", "rossi1": "", "rossi2": "", "goleador_1": "{}", "goleador_2": "{}", "autogol1": "{}", "autogol2": "{}", "best_giocatore_1": {}, "best_giocatore_2": {}, "best_portiere_1": {}, "best_portiere_2": {}, "note": ""}, "50": {"data": "08-13-2022 14:40:00", "gironi": "B Femminile", "genere_gironi": 0, "squadra_1": "MOCCIO(SE)", "squadra_2": "GREENPASSERE", "gol_squadra_1": 0, "gol_squadra_2": 0, "falli_squadra_1": 0, "falli_squadra_2": 0, "gialli1": "", "gialli2": "", "rossi1": "", "rossi2": "", "goleador_1": "{}", "goleador_2": "{}", "autogol1": "{}", "autogol2": "{}", "best_giocatore_1": {}, "best_giocatore_2": {}, "best_portiere_1": {}, "best_portiere_2": {}, "note": ""}, "51": {"data": "08-13-2022 15:00:00", "gironi": "E Maschile", "genere_gironi": 1, "squadra_1": "BUONA LA MERDA", "squadra_2": "MEDIASER.T", "gol_squadra_1": 0, "gol_squadra_2": 0, "falli_squadra_1": 0, "falli_squadra_2": 0, "gialli1": "", "gialli2": "", "rossi1": "", "rossi2": "", "goleador_1": "{}", "goleador_2": "{}", "autogol1": "{}", "autogol2": "{}", "best_giocatore_1": {}, "best_giocatore_2": {}, "best_portiere_1": {}, "best_portiere_2": {}, "note": ""}, "52": {"data": "08-13-2022 15:20:00", "gironi": "D Femminile", "genere_gironi": 0, "squadra_1": "FC WANDA TEAM GIRLS", "squadra_2": "CHICASMALAS", "gol_squadra_1": 0, "gol_squadra_2": 0, "falli_squadra_1": 0, "falli_squadra_2": 0, "gialli1": "", "gialli2": "", "rossi1": "", "rossi2": "", "goleador_1": "{}", "goleador_2": "{}", "autogol1": "{}", "autogol2": "{}", "best_giocatore_1": {}, "best_giocatore_2": {}, "best_portiere_1": {}, "best_portiere_2": {}, "note": ""}, "53": {"data": "08-13-2022 15:40:00", "gironi": "C Maschile", "genere_gironi": 1, "squadra_1": "I MONTAGNA", "squadra_2": "CLANDES TEAM", "gol_squadra_1": 0, "gol_squadra_2": 0, "falli_squadra_1": 0, "falli_squadra_2": 0, "gialli1": "", "gialli2": "", "rossi1": "", "rossi2": "", "goleador_1": "{}", "goleador_2": "{}", "autogol1": "{}", "autogol2": "{}", "best_giocatore_1": {}, "best_giocatore_2": {}, "best_portiere_1": {}, "best_portiere_2": {}, "note": ""}, "54": {"data": "08-13-2022 16:00:00", "gironi": "A Maschile", "genere_gironi": 1, "squadra_1": "FEL LAZIO", "squadra_2": "I MAGNIFICI", "gol_squadra_1": 0, "gol_squadra_2": 0, "falli_squadra_1": 0, "falli_squadra_2": 0, "gialli1": "", "gialli2": "", "rossi1": "", "rossi2": "", "goleador_1": "{}", "goleador_2": "{}", "autogol1": "{}", "autogol2": "{}", "best_giocatore_1": {}, "best_giocatore_2": {}, "best_portiere_1": {}, "best_portiere_2": {}, "note": ""}, "55": {"data": "08-13-2022 16:20:00", "gironi": "H Maschile", "genere_gironi": 1, "squadra_1": "LA CONTEA FC", "squadra_2": "RESENTEAM", "gol_squadra_1": 0, "gol_squadra_2": 0, "falli_squadra_1": 0, "falli_squadra_2": 0, "gialli1": "", "gialli2": "", "rossi1": "", "rossi2": "", "goleador_1": "{}", "goleador_2": "{}", "autogol1": "{}", "autogol2": "{}", "best_giocatore_1": {}, "best_giocatore_2": {}, "best_portiere_1": {}, "best_portiere_2": {}, "note": ""}, "56": {"data": "08-13-2022 16:40:00", "gironi": "F Maschile", "genere_gironi": 1, "squadra_1": "LIZZANELLA'S OLD SUGHI", "squadra_2": "CLITORIDERS", "gol_squadra_1": 0, "gol_squadra_2": 0, "falli_squadra_1": 0, "falli_squadra_2": 0, "gialli1": "", "gialli2": "", "rossi1": "", "rossi2": "", "goleador_1": "{}", "goleador_2": "{}", "autogol1": "{}", "autogol2": "{}", "best_giocatore_1": {}, "best_giocatore_2": {}, "best_portiere_1": {}, "best_portiere_2": {}, "note": ""}, "57": {"data": "08-13-2022 17:00:00", "gironi": "G Maschile", "genere_gironi": 1, "squadra_1": "ATLETICO MA NON TROPPO", "squadra_2": "DEMO BUSTERS", "gol_squadra_1": 0, "gol_squadra_2": 0, "falli_squadra_1": 0, "falli_squadra_2": 0, "gialli1": "", "gialli2": "", "rossi1": "", "rossi2": "", "goleador_1": "{}", "goleador_2": "{}", "autogol1": "{}", "autogol2": "{}", "best_giocatore_1": {}, "best_giocatore_2": {}, "best_portiere_1": {}, "best_portiere_2": {}, "note": ""}, "58": {"data": "08-13-2022 17:20:00", "gironi": "B Maschile", "genere_gironi": 1, "squadra_1": "MAI UNA GIOIA", "squadra_2": "US GUARNA", "gol_squadra_1": 0, "gol_squadra_2": 0, "falli_squadra_1": 0, "falli_squadra_2": 0, "gialli1": "", "gialli2": "", "rossi1": "", "rossi2": "", "goleador_1": "{}", "goleador_2": "{}", "autogol1": "{}", "autogol2": "{}", "best_giocatore_1": {}, "best_giocatore_2": {}, "best_portiere_1": {}, "best_portiere_2": {}, "note": ""}, "59": {"data": "08-13-2022 17:40:00", "gironi": "B Femminile", "genere_gironi": 0, "squadra_1": "GIN TONICHE", "squadra_2": "AL VOLO", "gol_squadra_1": 0, "gol_squadra_2": 0, "falli_squadra_1": 0, "falli_squadra_2": 0, "gialli1": "", "gialli2": "", "rossi1": "", "rossi2": "", "goleador_1": "{}", "goleador_2": "{}", "autogol1": "{}", "autogol2": "{}", "best_giocatore_1": {}, "best_giocatore_2": {}, "best_portiere_1": {}, "best_portiere_2": {}, "note": ""}, "60": {"data": "08-13-2022 18:00:00", "gironi": "G Maschile", "genere_gironi": 1, "squadra_1": "NAZIONALE FERROVIERI", "squadra_2": "POWER GINGER", "gol_squadra_1": 0, "gol_squadra_2": 0, "falli_squadra_1": 0, "falli_squadra_2": 0, "gialli1": "", "gialli2": "", "rossi1": "", "rossi2": "", "goleador_1": "{}", "goleador_2": "{}", "autogol1": "{}", "autogol2": "{}", "best_giocatore_1": {}, "best_giocatore_2": {}, "best_portiere_1": {}, "best_portiere_2": {}, "note": ""}, "61": {"data": "08-13-2022 18:20:00", "gironi": "C Femminile", "genere_gironi": 0, "squadra_1": "SAILOR MONE", "squadra_2": "TORTE DI MELE", "gol_squadra_1": 0, "gol_squadra_2": 0, "falli_squadra_1": 0, "falli_squadra_2": 0, "gialli1": "", "gialli2": "", "rossi1": "", "rossi2": "", "goleador_1": "{}", "goleador_2": "{}", "autogol1": "{}", "autogol2": "{}", "best_giocatore_1": {}, "best_giocatore_2": {}, "best_portiere_1": {}, "best_portiere_2": {}, "note": ""}, "62": {"data": "08-13-2022 18:40:00", "gironi": "C Maschile", "genere_gironi": 1, "squadra_1": "BELLA DOMANDA", "squadra_2": "CLANDES TEAM", "gol_squadra_1": 0, "gol_squadra_2": 0, "falli_squadra_1": 0, "falli_squadra_2": 0, "gialli1": "", "gialli2": "", "rossi1": "", "rossi2": "", "goleador_1": "{}", "goleador_2": "{}", "autogol1": "{}", "autogol2": "{}", "best_giocatore_1": {}, "best_giocatore_2": {}, "best_portiere_1": {}, "best_portiere_2": {}, "note": ""}, "63": {"data": "08-13-2022 19:00:00", "gironi": "A Femminile", "genere_gironi": 0, "squadra_1": "FOUR TAIE + 1", "squadra_2": "POCHE MA BONE", "gol_squadra_1": 0, "gol_squadra_2": 0, "falli_squadra_1": 0, "falli_squadra_2": 0, "gialli1": "", "gialli2": "", "rossi1": "", "rossi2": "", "goleador_1": "{}", "goleador_2": "{}", "autogol1": "{}", "autogol2": "{}", "best_giocatore_1": {}, "best_giocatore_2": {}, "best_portiere_1": {}, "best_portiere_2": {}, "note": ""}, "64": {"data": "08-13-2022 19:20:00", "gironi": "D Maschile", "genere_gironi": 1, "squadra_1": "ONLYFUK", "squadra_2": "ORANGE OLD SCHOOL", "gol_squadra_1": 0, "gol_squadra_2": 0, "falli_squadra_1": 0, "falli_squadra_2": 0, "gialli1": "", "gialli2": "", "rossi1": "", "rossi2": "", "goleador_1": "{}", "goleador_2": "{}", "autogol1": "{}", "autogol2": "{}", "best_giocatore_1": {}, "best_giocatore_2": {}, "best_portiere_1": {}, "best_portiere_2": {}, "note": ""}, "65": {"data": "08-13-2022 19:40:00", "gironi": "H Maschile", "genere_gironi": 1, "squadra_1": "LA CONTEA FC", "squadra_2": "INEFUMA ELEVEN", "gol_squadra_1": 0, "gol_squadra_2": 0, "falli_squadra_1": 0, "falli_squadra_2": 0, "gialli1": "", "gialli2": "", "rossi1": "", "rossi2": "", "goleador_1": "{}", "goleador_2": "{}", "autogol1": "{}", "autogol2": "{}", "best_giocatore_1": {}, "best_giocatore_2": {}, "best_portiere_1": {}, "best_portiere_2": {}, "note": ""}, "66": {"data": "08-13-2022 20:00:00", "gironi": "F Maschile", "genere_gironi": 1, "squadra_1": "CLITORIDERS", "squadra_2": "HELLAS MADONNA", "gol_squadra_1": 0, "gol_squadra_2": 0, "falli_squadra_1": 0, "falli_squadra_2": 0, "gialli1": "", "gialli2": "", "rossi1": "", "rossi2": "", "goleador_1": "{}", "goleador_2": "{}", "autogol1": "{}", "autogol2": "{}", "best_giocatore_1": {}, "best_giocatore_2": {}, "best_portiere_1": {}, "best_portiere_2": {}, "note": ""}, "67": {"data": "08-13-2022 21:00:00", "gironi": "C Maschile", "genere_gironi": 1, "squadra_1": "I MONTAGNA", "squadra_2": "PINGUINI TRENTINI", "gol_squadra_1": 0, "gol_squadra_2": 0, "falli_squadra_1": 0, "falli_squadra_2": 0, "gialli1": "", "gialli2": "", "rossi1": "", "rossi2": "", "goleador_1": "{}", "goleador_2": "{}", "autogol1": "{}", "autogol2": "{}", "best_giocatore_1": {}, "best_giocatore_2": {}, "best_portiere_1": {}, "best_portiere_2": {}, "note": ""}, "68": {"data": "08-13-2022 21:20:00", "gironi": "B Maschile", "genere_gironi": 1, "squadra_1": "MAI UNA GIOIA", "squadra_2": "PRATO FIORITO", "gol_squadra_1": 0, "gol_squadra_2": 0, "falli_squadra_1": 0, "falli_squadra_2": 0, "gialli1": "", "gialli2": "", "rossi1": "", "rossi2": "", "goleador_1": "{}", "goleador_2": "{}", "autogol1": "{}", "autogol2": "{}", "best_giocatore_1": {}, "best_giocatore_2": {}, "best_portiere_1": {}, "best_portiere_2": {}, "note": ""}, "69": {"data": "08-13-2022 21:40:00", "gironi": "QUARTI DONNE", "genere_gironi": 0, "squadra_1": "QUARTI DONNE", "squadra_2": "QUARTI DONNE", "gol_squadra_1": 0, "gol_squadra_2": 0, "falli_squadra_1": 0, "falli_squadra_2": 0, "gialli1": "", "gialli2": "", "rossi1": "", "rossi2": "", "goleador_1": "{}", "goleador_2": "{}", "autogol1": "{}", "autogol2": "{}", "best_giocatore_1": {}, "best_giocatore_2": {}, "best_portiere_1": {}, "best_portiere_2": {}, "note": ""}, "70": {"data": "08-13-2022 22:00:00", "gironi": "QUARTI DONNE", "genere_gironi": 0, "squadra_1": "QUARTI DONNE", "squadra_2": "QUARTI DONNE", "gol_squadra_1": 0, "gol_squadra_2": 0, "falli_squadra_1": 0, "falli_squadra_2": 0, "gialli1": "", "gialli2": "", "rossi1": "", "rossi2": "", "goleador_1": "{}", "goleador_2": "{}", "autogol1": "{}", "autogol2": "{}", "best_giocatore_1": {}, "best_giocatore_2": {}, "best_portiere_1": {}, "best_portiere_2": {}, "note": ""}, "71": {"data": "08-13-2022 22:20:00", "gironi": "A Maschile", "genere_gironi": 1, "squadra_1": "SHARK ATTACK", "squadra_2": "FC SAVIGNANO", "gol_squadra_1": 0, "gol_squadra_2": 0, "falli_squadra_1": 0, "falli_squadra_2": 0, "gialli1": "", "gialli2": "", "rossi1": "", "rossi2": "", "goleador_1": "{}", "goleador_2": "{}", "autogol1": "{}", "autogol2": "{}", "best_giocatore_1": {}, "best_giocatore_2": {}, "best_portiere_1": {}, "best_portiere_2": {}, "note": ""}, "72": {"data": "08-13-2022 22:40:00", "gironi": "E Maschile", "genere_gironi": 1, "squadra_1": "I MODIUM", "squadra_2": "BUONA LA MERDA", "gol_squadra_1": 0, "gol_squadra_2": 0, "falli_squadra_1": 0, "falli_squadra_2": 0, "gialli1": "", "gialli2": "", "rossi1": "", "rossi2": "", "goleador_1": "{}", "goleador_2": "{}", "autogol1": "{}", "autogol2": "{}", "best_giocatore_1": {}, "best_giocatore_2": {}, "best_portiere_1": {}, "best_portiere_2": {}, "note": ""}, "73": {"data": "08-13-2022 23:00:00", "gironi": "F Maschile", "genere_gironi": 1, "squadra_1": "LIZZANELLA'S OLD SUGHI", "squadra_2": "HELLAS MADONNA", "gol_squadra_1": 0, "gol_squadra_2": 0, "falli_squadra_1": 0, "falli_squadra_2": 0, "gialli1": "", "gialli2": "", "rossi1": "", "rossi2": "", "goleador_1": "{}", "goleador_2": "{}", "autogol1": "{}", "autogol2": "{}", "best_giocatore_1": {}, "best_giocatore_2": {}, "best_portiere_1": {}, "best_portiere_2": {}, "note": ""}, "74": {"data": "08-13-2022 23:20:00", "gironi": "QUARTI DONNE", "genere_gironi": 0, "squadra_1": "QUARTI DONNE", "squadra_2": "QUARTI DONNE", "gol_squadra_1": 0, "gol_squadra_2": 0, "falli_squadra_1": 0, "falli_squadra_2": 0, "gialli1": "", "gialli2": "", "rossi1": "", "rossi2": "", "goleador_1": "{}", "goleador_2": "{}", "autogol1": "{}", "autogol2": "{}", "best_giocatore_1": {}, "best_giocatore_2": {}, "best_portiere_1": {}, "best_portiere_2": {}, "note": ""}, "75": {"data": "08-13-2022 23:40:00", "gironi": "QUARTI DONNE", "genere_gironi": 0, "squadra_1": "QUARTI DONNE", "squadra_2": "QUARTI DONNE", "gol_squadra_1": 0, "gol_squadra_2": 0, "falli_squadra_1": 0, "falli_squadra_2": 0, "gialli1": "", "gialli2": "", "rossi1": "", "rossi2": "", "goleador_1": "{}", "goleador_2": "{}", "autogol1": "{}", "autogol2": "{}", "best_giocatore_1": {}, "best_giocatore_2": {}, "best_portiere_1": {}, "best_portiere_2": {}, "note": ""}, "76": {"data": "08-14-2022 10:00:00", "gironi": "OTTAVI UOMINI", "genere_gironi": 1, "squadra_1": "OTTAVI UOMINI", "squadra_2": "OTTAVI UOMINI", "gol_squadra_1": 0, "gol_squadra_2": 0, "falli_squadra_1": 0, "falli_squadra_2": 0, "gialli1": "", "gialli2": "", "rossi1": "", "rossi2": "", "goleador_1": "{}", "goleador_2": "{}", "autogol1": "{}", "autogol2": "{}", "best_giocatore_1": {}, "best_giocatore_2": {}, "best_portiere_1": {}, "best_portiere_2": {}, "note": ""}, "77": {"data": "08-14-2022 10:20:00", "gironi": "OTTAVI UOMINI", "genere_gironi": 1, "squadra_1": "OTTAVI UOMINI", "squadra_2": "OTTAVI UOMINI", "gol_squadra_1": 0, "gol_squadra_2": 0, "falli_squadra_1": 0, "falli_squadra_2": 0, "gialli1": "", "gialli2": "", "rossi1": "", "rossi2": "", "goleador_1": "{}", "goleador_2": "{}", "autogol1": "{}", "autogol2": "{}", "best_giocatore_1": {}, "best_giocatore_2": {}, "best_portiere_1": {}, "best_portiere_2": {}, "note": ""}, "78": {"data": "08-14-2022 10:40:00", "gironi": "OTTAVI UOMINI", "genere_gironi": 1, "squadra_1": "OTTAVI UOMINI", "squadra_2": "OTTAVI UOMINI", "gol_squadra_1": 0, "gol_squadra_2": 0, "falli_squadra_1": 0, "falli_squadra_2": 0, "gialli1": "", "gialli2": "", "rossi1": "", "rossi2": "", "goleador_1": "{}", "goleador_2": "{}", "autogol1": "{}", "autogol2": "{}", "best_giocatore_1": {}, "best_giocatore_2": {}, "best_portiere_1": {}, "best_portiere_2": {}, "note": ""}, "79": {"data": "08-14-2022 11:00:00", "gironi": "OTTAVI UOMINI", "genere_gironi": 1, "squadra_1": "OTTAVI UOMINI", "squadra_2": "OTTAVI UOMINI", "gol_squadra_1": 0, "gol_squadra_2": 0, "falli_squadra_1": 0, "falli_squadra_2": 0, "gialli1": "", "gialli2": "", "rossi1": "", "rossi2": "", "goleador_1": "{}", "goleador_2": "{}", "autogol1": "{}", "autogol2": "{}", "best_giocatore_1": {}, "best_giocatore_2": {}, "best_portiere_1": {}, "best_portiere_2": {}, "note": ""}, "80": {"data": "08-14-2022 11:20:00", "gironi": "OTTAVI UOMINI", "genere_gironi": 1, "squadra_1": "OTTAVI UOMINI", "squadra_2": "OTTAVI UOMINI", "gol_squadra_1": 0, "gol_squadra_2": 0, "falli_squadra_1": 0, "falli_squadra_2": 0, "gialli1": "", "gialli2": "", "rossi1": "", "rossi2": "", "goleador_1": "{}", "goleador_2": "{}", "autogol1": "{}", "autogol2": "{}", "best_giocatore_1": {}, "best_giocatore_2": {}, "best_portiere_1": {}, "best_portiere_2": {}, "note": ""}, "81": {"data": "08-14-2022 11:40:00", "gironi": "OTTAVI UOMINI", "genere_gironi": 1, "squadra_1": "OTTAVI UOMINI", "squadra_2": "OTTAVI UOMINI", "gol_squadra_1": 0, "gol_squadra_2": 0, "falli_squadra_1": 0, "falli_squadra_2": 0, "gialli1": "", "gialli2": "", "rossi1": "", "rossi2": "", "goleador_1": "{}", "goleador_2": "{}", "autogol1": "{}", "autogol2": "{}", "best_giocatore_1": {}, "best_giocatore_2": {}, "best_portiere_1": {}, "best_portiere_2": {}, "note": ""}, "82": {"data": "08-14-2022 12:00:00", "gironi": "OTTAVI UOMINI", "genere_gironi": 1, "squadra_1": "OTTAVI UOMINI", "squadra_2": "OTTAVI UOMINI", "gol_squadra_1": 0, "gol_squadra_2": 0, "falli_squadra_1": 0, "falli_squadra_2": 0, "gialli1": "", "gialli2": "", "rossi1": "", "rossi2": "", "goleador_1": "{}", "goleador_2": "{}", "autogol1": "{}", "autogol2": "{}", "best_giocatore_1": {}, "best_giocatore_2": {}, "best_portiere_1": {}, "best_portiere_2": {}, "note": ""}, "83": {"data": "08-14-2022 12:20:00", "gironi": "OTTAVI UOMINI", "genere_gironi": 1, "squadra_1": "OTTAVI UOMINI", "squadra_2": "OTTAVI UOMINI", "gol_squadra_1": 0, "gol_squadra_2": 0, "falli_squadra_1": 0, "falli_squadra_2": 0, "gialli1": "", "gialli2": "", "rossi1": "", "rossi2": "", "goleador_1": "{}", "goleador_2": "{}", "autogol1": "{}", "autogol2": "{}", "best_giocatore_1": {}, "best_giocatore_2": {}, "best_portiere_1": {}, "best_portiere_2": {}, "note": ""}, "84": {"data": "08-14-2022 14:40:00", "gironi": "QUARTI UOMINI", "genere_gironi": 1, "squadra_1": "QUARTI UOMINI", "squadra_2": "QUARTI UOMINI", "gol_squadra_1": 0, "gol_squadra_2": 0, "falli_squadra_1": 0, "falli_squadra_2": 0, "gialli1": "", "gialli2": "", "rossi1": "", "rossi2": "", "goleador_1": "{}", "goleador_2": "{}", "autogol1": "{}", "autogol2": "{}", "best_giocatore_1": {}, "best_giocatore_2": {}, "best_portiere_1": {}, "best_portiere_2": {}, "note": ""}, "85": {"data": "08-14-2022 15:10:00", "gironi": "QUARTI UOMINI", "genere_gironi": 1, "squadra_1": "QUARTI UOMINI", "squadra_2": "QUARTI UOMINI", "gol_squadra_1": 0, "gol_squadra_2": 0, "falli_squadra_1": 0, "falli_squadra_2": 0, "gialli1": "", "gialli2": "", "rossi1": "", "rossi2": "", "goleador_1": "{}", "goleador_2": "{}", "autogol1": "{}", "autogol2": "{}", "best_giocatore_1": {}, "best_giocatore_2": {}, "best_portiere_1": {}, "best_portiere_2": {}, "note": ""}, "86": {"data": "08-14-2022 15:40:00", "gironi": "QUARTI UOMINI", "genere_gironi": 1, "squadra_1": "QUARTI UOMINI", "squadra_2": "QUARTI UOMINI", "gol_squadra_1": 0, "gol_squadra_2": 0, "falli_squadra_1": 0, "falli_squadra_2": 0, "gialli1": "", "gialli2": "", "rossi1": "", "rossi2": "", "goleador_1": "{}", "goleador_2": "{}", "autogol1": "{}", "autogol2": "{}", "best_giocatore_1": {}, "best_giocatore_2": {}, "best_portiere_1": {}, "best_portiere_2": {}, "note": ""}, "87": {"data": "08-14-2022 16:10:00", "gironi": "QUARTI UOMINI", "genere_gironi": 1, "squadra_1": "QUARTI UOMINI", "squadra_2": "QUARTI UOMINI", "gol_squadra_1": 0, "gol_squadra_2": 0, "falli_squadra_1": 0, "falli_squadra_2": 0, "gialli1": "", "gialli2": "", "rossi1": "", "rossi2": "", "goleador_1": "{}", "goleador_2": "{}", "autogol1": "{}", "autogol2": "{}", "best_giocatore_1": {}, "best_giocatore_2": {}, "best_portiere_1": {}, "best_portiere_2": {}, "note": ""}, "88": {"data": "08-14-2022 16:30:00", "gironi": "SPAREGGI DONNE", "genere_gironi": 0, "squadra_1": "15 DONNE", "squadra_2": "16 DONNE", "gol_squadra_1": 0, "gol_squadra_2": 0, "falli_squadra_1": 0, "falli_squadra_2": 0, "gialli1": "", "gialli2": "", "rossi1": "", "rossi2": "", "goleador_1": "{}", "goleador_2": "{}", "autogol1": "{}", "autogol2": "{}", "best_giocatore_1": {}, "best_giocatore_2": {}, "best_portiere_1": {}, "best_portiere_2": {}, "note": ""}, "89": {"data": "08-14-2022 16:50:00", "gironi": "SPAREGGI DONNE", "genere_gironi": 0, "squadra_1": "13 DONNE", "squadra_2": "14 DONNE", "gol_squadra_1": 0, "gol_squadra_2": 0, "falli_squadra_1": 0, "falli_squadra_2": 0, "gialli1": "", "gialli2": "", "rossi1": "", "rossi2": "", "goleador_1": "{}", "goleador_2": "{}", "autogol1": "{}", "autogol2": "{}", "best_giocatore_1": {}, "best_giocatore_2": {}, "best_portiere_1": {}, "best_portiere_2": {}, "note": ""}, "90": {"data": "08-14-2022 17:10:00", "gironi": "SPAREGGI DONNE", "genere_gironi": 0, "squadra_1": "12 DONNE", "squadra_2": "11 DONNE", "gol_squadra_1": 0, "gol_squadra_2": 0, "falli_squadra_1": 0, "falli_squadra_2": 0, "gialli1": "", "gialli2": "", "rossi1": "", "rossi2": "", "goleador_1": "{}", "goleador_2": "{}", "autogol1": "{}", "autogol2": "{}", "best_giocatore_1": {}, "best_giocatore_2": {}, "best_portiere_1": {}, "best_portiere_2": {}, "note": ""}, "91": {"data": "08-14-2022 17:30:00", "gironi": "SPAREGGI DONNE", "genere_gironi": 0, "squadra_1": "10 DONNE", "squadra_2": "9 DONNE", "gol_squadra_1": 0, "gol_squadra_2": 0, "falli_squadra_1": 0, "falli_squadra_2": 0, "gialli1": "", "gialli2": "", "rossi1": "", "rossi2": "", "goleador_1": "{}", "goleador_2": "{}", "autogol1": "{}", "autogol2": "{}", "best_giocatore_1": {}, "best_giocatore_2": {}, "best_portiere_1": {}, "best_portiere_2": {}, "note": ""}, "92": {"data": "08-14-2022 18:00:00", "gironi": "SEMIFINALE DONNE", "genere_gironi": 0, "squadra_1": "SEMIFINALE DONNE", "squadra_2": "SEMIFINALE DONNE", "gol_squadra_1": 0, "gol_squadra_2": 0, "falli_squadra_1": 0, "falli_squadra_2": 0, "gialli1": "", "gialli2": "", "rossi1": "", "rossi2": "", "goleador_1": "{}", "goleador_2": "{}", "autogol1": "{}", "autogol2": "{}", "best_giocatore_1": {}, "best_giocatore_2": {}, "best_portiere_1": {}, "best_portiere_2": {}, "note": ""}, "93": {"data": "08-14-2022 18:30:00", "gironi": "SEMIFINALE UOMINI", "genere_gironi": 1, "squadra_1": "SEMIFINALE UOMINI", "squadra_2": "SEMIFINALE UOMINI", "gol_squadra_1": 0, "gol_squadra_2": 0, "falli_squadra_1": 0, "falli_squadra_2": 0, "gialli1": "", "gialli2": "", "rossi1": "", "rossi2": "", "goleador_1": "{}", "goleador_2": "{}", "autogol1": "{}", "autogol2": "{}", "best_giocatore_1": {}, "best_giocatore_2": {}, "best_portiere_1": {}, "best_portiere_2": {}, "note": ""}, "94": {"data": "08-14-2022 19:00:00", "gironi": "SEMIFINALE UOMINI", "genere_gironi": 0, "squadra_1": "SEMIFINALE DONNE ", "squadra_2": "SEMIFINALE DONNE", "gol_squadra_1": 0, "gol_squadra_2": 0, "falli_squadra_1": 0, "falli_squadra_2": 0, "gialli1": "", "gialli2": "", "rossi1": "", "rossi2": "", "goleador_1": "{}", "goleador_2": "{}", "autogol1": "{}", "autogol2": "{}", "best_giocatore_1": {}, "best_giocatore_2": {}, "best_portiere_1": {}, "best_portiere_2": {}, "note": ""}, "95": {"data": "08-14-2022 19:30:00", "gironi": "SEMIFINALE UOMINI", "genere_gironi": 1, "squadra_1": "SEMIFINALE UOMINI", "squadra_2": "SEMIFINALE UOMINI", "gol_squadra_1": 0, "gol_squadra_2": 0, "falli_squadra_1": 0, "falli_squadra_2": 0, "gialli1": "", "gialli2": "", "rossi1": "", "rossi2": "", "goleador_1": "{}", "goleador_2": "{}", "autogol1": "{}", "autogol2": "{}", "best_giocatore_1": {}, "best_giocatore_2": {}, "best_portiere_1": {}, "best_portiere_2": {}, "note": ""}, "96": {"data": "08-14-2022 20:30:00", "gironi": "FINALINA DONNE", "genere_gironi": 0, "squadra_1": "FINALE 3-4 DONNE", "squadra_2": "FINALE 3-4 DONNE", "gol_squadra_1": 0, "gol_squadra_2": 0, "falli_squadra_1": 0, "falli_squadra_2": 0, "gialli1": "", "gialli2": "", "rossi1": "", "rossi2": "", "goleador_1": "{}", "goleador_2": "{}", "autogol1": "{}", "autogol2": "{}", "best_giocatore_1": {}, "best_giocatore_2": {}, "best_portiere_1": {}, "best_portiere_2": {}, "note": ""}, "97": {"data": "08-14-2022 21:00:00", "gironi": "FINALINA UOMINI", "genere_gironi": 1, "squadra_1": "FINALE 3-4 UOMINI", "squadra_2": "FINALE 3-4 UOMINI", "gol_squadra_1": 0, "gol_squadra_2": 0, "falli_squadra_1": 0, "falli_squadra_2": 0, "gialli1": "", "gialli2": "", "rossi1": "", "rossi2": "", "goleador_1": "{}", "goleador_2": "{}", "autogol1": "{}", "autogol2": "{}", "best_giocatore_1": {}, "best_giocatore_2": {}, "best_portiere_1": {}, "best_portiere_2": {}, "note": ""}, "98": {"data": "08-14-2022 21:30:00", "gironi": "FINALISSIMA DONNE", "genere_gironi": 0, "squadra_1": "FINALISSIMA DONNE", "squadra_2": "FINALISSIMA DONNE", "gol_squadra_1": 0, "gol_squadra_2": 0, "falli_squadra_1": 0, "falli_squadra_2": 0, "gialli1": "", "gialli2": "", "rossi1": "", "rossi2": "", "goleador_1": "{}", "goleador_2": "{}", "autogol1": "{}", "autogol2": "{}", "best_giocatore_1": {}, "best_giocatore_2": {}, "best_portiere_1": {}, "best_portiere_2": {}, "note": ""}, "99": {"data": "08-14-2022 22:00:00", "gironi": "FINALISSIMA UOMINI", "genere_gironi": 1, "squadra_1": "FINALISSIMA UOMINI", "squadra_2": "FINALISSIMA UOMINI", "gol_squadra_1": 0, "gol_squadra_2": 0, "falli_squadra_1": 0, "falli_squadra_2": 0, "gialli1": "", "gialli2": "", "rossi1": "", "rossi2": "", "goleador_1": "{}", "goleador_2": "{}", "autogol1": "{}", "autogol2": "{}", "best_giocatore_1": {}, "best_giocatore_2": {}, "best_portiere_1": {}, "best_portiere_2": {}, "note": ""}}}